{
  "SPDXID" : "SPDXRef-DOCUMENT",
  "spdxVersion" : "SPDX-2.3",
  "creationInfo" : {
    "comment" : "Converted from CycloneDX spec version 1.4",
    "created" : "2023-07-17T15:47:32Z",
    "creators" : [ "Tool: CycloneDX:cyclonedx-bom-3.11.2", "Tool: CycloneDX:cyclonedx-python-lib-3.1.1", "Tool: CycloneToSpdx-0.1.4" ],
    "licenseListVersion" : "3.21"
  },
  "name" : "From-Cyclone-DX",
  "dataLicense" : "CC0-1.0",
  "annotations" : [ {
    "annotationDate" : "2023-07-17T15:47:34Z",
    "annotationType" : "OTHER",
    "annotator" : "Tool: CycloneToSpdx",
    "comment" : "MISSING_CDX_PROPERTY:extensions={}"
  } ],
  "documentNamespace" : "https://cyclonedx/c95221a4-7b76-444a-8f46-cf4001b9de76_1",
  "packages" : [ {
    "SPDXID" : "SPDXRef-c051c3e4-f2e3-46a0-954e-d404a40a011b",
    "annotations" : [ {
      "annotationDate" : "2023-07-17T15:47:34Z",
      "annotationType" : "OTHER",
      "annotator" : "Tool: CycloneToSpdx",
      "comment" : "MISSING_CDX_PROPERTY:componentType=\"LIBRARY\""
    } ],
    "copyrightText" : "NOASSERTION",
    "downloadLocation" : "NOASSERTION",
    "externalRefs" : [ {
      "referenceCategory" : "PACKAGE-MANAGER",
      "referenceLocator" : "pkg:pypi/pandoc@2.3",
      "referenceType" : "purl"
    } ],
    "filesAnalyzed" : false,
    "licenseConcluded" : "NOASSERTION",
    "licenseDeclared" : "NOASSERTION",
    "name" : "pandoc",
    "primaryPackagePurpose" : "LIBRARY",
    "versionInfo" : "2.3"
  }, {
    "SPDXID" : "SPDXRef-a6b0d348-7e01-4fa6-a7f9-f0e63a66daf5",
    "annotations" : [ {
      "annotationDate" : "2023-07-17T15:47:34Z",
      "annotationType" : "OTHER",
      "annotator" : "Tool: CycloneToSpdx",
      "comment" : "MISSING_CDX_PROPERTY:componentType=\"LIBRARY\""
    } ],
    "copyrightText" : "NOASSERTION",
    "downloadLocation" : "NOASSERTION",
    "externalRefs" : [ {
      "referenceCategory" : "PACKAGE-MANAGER",
      "referenceLocator" : "pkg:pypi/pydantic@1.10.10",
      "referenceType" : "purl"
    } ],
    "filesAnalyzed" : false,
    "licenseConcluded" : "NOASSERTION",
    "licenseDeclared" : "NOASSERTION",
    "name" : "pydantic",
    "primaryPackagePurpose" : "LIBRARY",
    "versionInfo" : "1.10.10"
  }, {
    "SPDXID" : "SPDXRef-797578ee-ed4e-4fc4-99e7-bd857c817b45",
    "annotations" : [ {
      "annotationDate" : "2023-07-17T15:47:34Z",
      "annotationType" : "OTHER",
      "annotator" : "Tool: CycloneToSpdx",
      "comment" : "MISSING_CDX_PROPERTY:componentType=\"LIBRARY\""
    } ],
    "copyrightText" : "NOASSERTION",
    "downloadLocation" : "NOASSERTION",
    "externalRefs" : [ {
      "referenceCategory" : "PACKAGE-MANAGER",
      "referenceLocator" : "pkg:pypi/typer@0.9.0",
      "referenceType" : "purl"
    } ],
    "filesAnalyzed" : false,
    "licenseConcluded" : "NOASSERTION",
    "licenseDeclared" : "NOASSERTION",
    "name" : "typer",
    "primaryPackagePurpose" : "LIBRARY",
    "versionInfo" : "0.9.0"
  }, {
    "SPDXID" : "SPDXRef-4c577a06-0737-406d-82b1-f8aed22f6039",
    "annotations" : [ {
      "annotationDate" : "2023-07-17T15:47:34Z",
      "annotationType" : "OTHER",
      "annotator" : "Tool: CycloneToSpdx",
      "comment" : "MISSING_CDX_PROPERTY:componentType=\"LIBRARY\""
    } ],
    "copyrightText" : "NOASSERTION",
    "downloadLocation" : "NOASSERTION",
    "externalRefs" : [ {
      "referenceCategory" : "PACKAGE-MANAGER",
      "referenceLocator" : "pkg:pypi/markdown@3.4.3",
      "referenceType" : "purl"
    } ],
    "filesAnalyzed" : false,
    "licenseConcluded" : "NOASSERTION",
    "licenseDeclared" : "NOASSERTION",
    "name" : "markdown",
    "primaryPackagePurpose" : "LIBRARY",
    "versionInfo" : "3.4.3"
  } ],
  "relationships" : [ {
    "spdxElementId" : "SPDXRef-DOCUMENT",
    "relationshipType" : "DESCRIBES",
    "relatedSpdxElement" : "SPDXRef-c051c3e4-f2e3-46a0-954e-d404a40a011b"
  }, {
    "spdxElementId" : "SPDXRef-DOCUMENT",
    "relationshipType" : "DESCRIBES",
    "relatedSpdxElement" : "SPDXRef-4c577a06-0737-406d-82b1-f8aed22f6039"
  }, {
    "spdxElementId" : "SPDXRef-DOCUMENT",
    "relationshipType" : "DESCRIBES",
    "relatedSpdxElement" : "SPDXRef-797578ee-ed4e-4fc4-99e7-bd857c817b45"
  }, {
    "spdxElementId" : "SPDXRef-DOCUMENT",
    "relationshipType" : "DESCRIBES",
    "relatedSpdxElement" : "SPDXRef-a6b0d348-7e01-4fa6-a7f9-f0e63a66daf5"
  } ]
}