{
  "SPDXID" : "SPDXRef-DOCUMENT",
  "spdxVersion" : "SPDX-2.3",
  "creationInfo" : {
    "comment" : "Converted from CycloneDX spec version 1.4",
    "created" : "2023-11-13T17:25:01Z",
    "creators" : [ "Tool: CycloneDX:cyclonedx-bom-3.11.7", "Tool: CycloneDX:cyclonedx-python-lib-3.1.5", "Tool: CycloneToSpdx-0.1.4" ],
    "licenseListVersion" : "3.22"
  },
  "name" : "From-Cyclone-DX",
  "dataLicense" : "CC0-1.0",
  "annotations" : [ {
    "annotationDate" : "2023-11-13T17:25:02Z",
    "annotationType" : "OTHER",
    "annotator" : "Tool: CycloneToSpdx",
    "comment" : "MISSING_CDX_PROPERTY:extensions={}"
  } ],
  "documentNamespace" : "https://cyclonedx/303f8f83-3c38-4689-a722-abd2d6efd8b2_1",
  "packages" : [ {
    "SPDXID" : "SPDXRef-79642f20-2090-4cb5-ba2e-2a4d11e145b9",
    "annotations" : [ {
      "annotationDate" : "2023-11-13T17:25:02Z",
      "annotationType" : "OTHER",
      "annotator" : "Tool: CycloneToSpdx",
      "comment" : "MISSING_CDX_PROPERTY:componentType=\"LIBRARY\""
    } ],
    "copyrightText" : "NOASSERTION",
    "downloadLocation" : "NOASSERTION",
    "externalRefs" : [ {
      "referenceCategory" : "PACKAGE-MANAGER",
      "referenceLocator" : "pkg:pypi/typer@0.9.0",
      "referenceType" : "purl"
    } ],
    "filesAnalyzed" : false,
    "licenseConcluded" : "NOASSERTION",
    "licenseDeclared" : "NOASSERTION",
    "name" : "typer",
    "primaryPackagePurpose" : "LIBRARY",
    "versionInfo" : "0.9.0"
  }, {
    "SPDXID" : "SPDXRef-35329f19-9ca5-41b4-a62a-8b5c3c733547",
    "annotations" : [ {
      "annotationDate" : "2023-11-13T17:25:02Z",
      "annotationType" : "OTHER",
      "annotator" : "Tool: CycloneToSpdx",
      "comment" : "MISSING_CDX_PROPERTY:componentType=\"LIBRARY\""
    } ],
    "copyrightText" : "NOASSERTION",
    "downloadLocation" : "NOASSERTION",
    "externalRefs" : [ {
      "referenceCategory" : "PACKAGE-MANAGER",
      "referenceLocator" : "pkg:pypi/markdown@3.5.1",
      "referenceType" : "purl"
    } ],
    "filesAnalyzed" : false,
    "licenseConcluded" : "NOASSERTION",
    "licenseDeclared" : "NOASSERTION",
    "name" : "markdown",
    "primaryPackagePurpose" : "LIBRARY",
    "versionInfo" : "3.5.1"
  }, {
    "SPDXID" : "SPDXRef-b13f74d6-9815-4b25-9647-ed8cd764815b",
    "annotations" : [ {
      "annotationDate" : "2023-11-13T17:25:02Z",
      "annotationType" : "OTHER",
      "annotator" : "Tool: CycloneToSpdx",
      "comment" : "MISSING_CDX_PROPERTY:componentType=\"LIBRARY\""
    } ],
    "copyrightText" : "NOASSERTION",
    "downloadLocation" : "NOASSERTION",
    "externalRefs" : [ {
      "referenceCategory" : "PACKAGE-MANAGER",
      "referenceLocator" : "pkg:pypi/pandoc@2.3",
      "referenceType" : "purl"
    } ],
    "filesAnalyzed" : false,
    "licenseConcluded" : "NOASSERTION",
    "licenseDeclared" : "NOASSERTION",
    "name" : "pandoc",
    "primaryPackagePurpose" : "LIBRARY",
    "versionInfo" : "2.3"
  }, {
    "SPDXID" : "SPDXRef-fc023875-4524-4d45-a9c1-20f74c3c63d9",
    "annotations" : [ {
      "annotationDate" : "2023-11-13T17:25:02Z",
      "annotationType" : "OTHER",
      "annotator" : "Tool: CycloneToSpdx",
      "comment" : "MISSING_CDX_PROPERTY:componentType=\"LIBRARY\""
    } ],
    "copyrightText" : "NOASSERTION",
    "downloadLocation" : "NOASSERTION",
    "externalRefs" : [ {
      "referenceCategory" : "PACKAGE-MANAGER",
      "referenceLocator" : "pkg:pypi/pydantic@2.5.0",
      "referenceType" : "purl"
    } ],
    "filesAnalyzed" : false,
    "licenseConcluded" : "NOASSERTION",
    "licenseDeclared" : "NOASSERTION",
    "name" : "pydantic",
    "primaryPackagePurpose" : "LIBRARY",
    "versionInfo" : "2.5.0"
  } ],
  "relationships" : [ {
    "spdxElementId" : "SPDXRef-DOCUMENT",
    "relationshipType" : "DESCRIBES",
    "relatedSpdxElement" : "SPDXRef-b13f74d6-9815-4b25-9647-ed8cd764815b"
  }, {
    "spdxElementId" : "SPDXRef-DOCUMENT",
    "relationshipType" : "DESCRIBES",
    "relatedSpdxElement" : "SPDXRef-35329f19-9ca5-41b4-a62a-8b5c3c733547"
  }, {
    "spdxElementId" : "SPDXRef-DOCUMENT",
    "relationshipType" : "DESCRIBES",
    "relatedSpdxElement" : "SPDXRef-79642f20-2090-4cb5-ba2e-2a4d11e145b9"
  }, {
    "spdxElementId" : "SPDXRef-DOCUMENT",
    "relationshipType" : "DESCRIBES",
    "relatedSpdxElement" : "SPDXRef-fc023875-4524-4d45-a9c1-20f74c3c63d9"
  } ]
}